burf/__init__.py
burf/burf.py
burf/deleter_screen.py
burf/downloader_screen.py
burf/error_screen.py
burf/file_list_view.py
burf/listing_service.py
burf/search_box.py
burf/string_getter.py
burf/util.py
burf/storage/ds.py
burf/storage/storage.py
burf-1.4.0.dist-info/METADATA
burf-1.4.0.dist-info/WHEEL
burf-1.4.0.dist-info/entry_points.txt
burf-1.4.0.dist-info/licenses/LICENSE
burf-1.4.0.dist-info/RECORD
