Metadata-Version: 2.4
Name: burf
Version: 1.4.0
Summary: A tool to surf buckets on gcs
Project-URL: Homepage, https://github.com/razeghi71/burf
Project-URL: Repository, https://github.com/razeghi71/burf
Author-email: Mohammad Razeghi <razeghi71@gmail.com>
License: MIT License
License-File: LICENSE
Keywords: gcs,google-cloud-storage,textual,tui
Classifier: Development Status :: 3 - Alpha
Classifier: Intended Audience :: Developers
Classifier: License :: OSI Approved :: MIT License
Classifier: Programming Language :: Python :: 3
Classifier: Programming Language :: Python :: 3 :: Only
Classifier: Programming Language :: Python :: 3.10
Classifier: Programming Language :: Python :: 3.11
Classifier: Programming Language :: Python :: 3.12
Requires-Python: >=3.10
Requires-Dist: google-cloud-storage==2.10.0
Requires-Dist: textual==0.28.1
